reverse_patch/__init__.py
reverse_patch/patch_logger.py
reverse_patch/reverse_patch_itself.py
reverse_patch/reverse_patch_utils.py
reverse_patch/testing_fixtures.py
reverse_patch-1.0.0.dist-info/LICENSE
reverse_patch-1.0.0.dist-info/METADATA
reverse_patch-1.0.0.dist-info/WHEEL
reverse_patch-1.0.0.dist-info/top_level.txt
reverse_patch-1.0.0.dist-info/RECORD
